aide/__init__.py
aide/messaging/__init__.py
aide/messaging/consumer.py
aide/messaging/exceptions.py
aide/messaging/publisher.py
aide/messaging/queue_config.py
aide/pacs_client/__init__.py
aide/pacs_client/pacs_client.py
aide/pacs_client/pacs_config.py
aide_infra-0.3.9.dist-info/LICENSE.md
aide_infra-0.3.9.dist-info/WHEEL
aide_infra-0.3.9.dist-info/METADATA
aide_infra-0.3.9.dist-info/RECORD
