Metadata-Version: 2.1
Name: aide-infra
Version: 0.3.9
Summary: 
Author: Josh Liberty
Author-email: josh.liberty@answerdigital.com
Requires-Python: >=3.7,<4.0
Classifier: Programming Language :: Python :: 3
Classifier: Programming Language :: Python :: 3.10
Classifier: Programming Language :: Python :: 3.7
Classifier: Programming Language :: Python :: 3.8
Classifier: Programming Language :: Python :: 3.9
Requires-Dist: pika (>=1.2.0,<2.0.0)
Requires-Dist: pydicom (==2.1.2)
Requires-Dist: pynetdicom (==1.5.7)
